{"type":"FeatureCollection","features":[{"type":"Feature","geometry":{"type":"Point","coordinates":[11.2543,43.77291]},"properties":{"level":"parent","id":0,"rank":0,"users":33,"peak":1.0,"prom":0.702,"radius_m":474,"peak_at":[11.25372,43.77592],"name":"Central Market","type":"culture"}},{"type":"Feature","geometry":{"type":"Point","coordinates":[11.18442,43.80818]},"properties":{"level":"parent","id":1,"rank":1,"users":1,"peak":0.366,"prom":0.366,"radius_m":120,"peak_at":[11.18442,43.80818]}},{"type":"Feature","geometry":{"type":"Point","coordinates":[11.18258,43.67031]},"properties":{"level":"parent","id":2,"rank":2,"users":1,"peak":0.366,"prom":0.366,"radius_m":120,"peak_at":[11.18258,43.67031]}},{"type":"Feature","geometry":{"type":"Point","coordinates":[11.19142,43.77233]},"properties":{"level":"parent","id":3,"rank":3,"users":1,"peak":0.366,"prom":0.366,"radius_m":120,"peak_at":[11.19142,43.77233],"name":"UCI Cinemas","type":"culture"}},{"type":"Feature","geometry":{"type":"Point","coordinates":[11.2577,43.78248]},"properties":{"level":"parent","id":4,"rank":4,"users":6,"peak":0.414,"prom":0.0,"radius_m":208,"peak_at":[11.25934,43.7833],"name":"Porta San Gallo","type":"culture"}},{"type":"Feature","geometry":{"type":"Point","coordinates":[11.25421,43.77613]},"properties":{"level":"child","parent":0,"users":12,"peak":1.0,"prom":0.388,"radius_m":183,"peak_at":[11.25372,43.77592],"name":"Central Market","type":"culture"}},{"type":"Feature","geometry":{"type":"Point","coordinates":[11.25493,43.77016]},"properties":{"level":"child","parent":0,"users":9,"peak":0.67,"prom":0.017,"radius_m":183,"peak_at":[11.25417,43.76998],"name":"Mercato del Porcellino","type":"culture"}}]}